karpentermig/__init__.py
karpentermig/cli.py
karpentermig/discover_cluster.py
test/__init__.py
test/test_karpentermig.py
karpentermig-0.1.0.dist-info/LICENSE
karpentermig-0.1.0.dist-info/METADATA
karpentermig-0.1.0.dist-info/WHEEL
karpentermig-0.1.0.dist-info/entry_points.txt
karpentermig-0.1.0.dist-info/top_level.txt
karpentermig-0.1.0.dist-info/RECORD
