Metadata-Version: 2.1
Name: karpentermig
Version: 0.1.0
Summary: A tool for Karpenter migration
Author: Pugar Jayanegara
License: Copyright <2024> <PUGAR JAYANEGARA>
Classifier: Programming Language :: Python :: 3
Classifier: License :: OSI Approved :: MIT License
Classifier: Operating System :: OS Independent
License-File: LICENSE
Requires-Dist: questionary
Requires-Dist: boto3
Requires-Dist: click
